{
	"cmake" : 
	{
		"generator" : 
		{
			"multiConfig" : false,
			"name" : "Ninja"
		},
		"paths" : 
		{
			"cmake" : "/home/jcc/package/clion-2021.3.2/bin/cmake/linux/bin/cmake",
			"cpack" : "/home/jcc/package/clion-2021.3.2/bin/cmake/linux/bin/cpack",
			"ctest" : "/home/jcc/package/clion-2021.3.2/bin/cmake/linux/bin/ctest",
			"root" : "/home/jcc/package/clion-2021.3.2/bin/cmake/linux/share/cmake-3.21"
		},
		"version" : 
		{
			"isDirty" : false,
			"major" : 3,
			"minor" : 21,
			"patch" : 1,
			"string" : "3.21.1",
			"suffix" : ""
		}
	},
	"objects" : 
	[
		{
			"jsonFile" : "codemodel-v2-d9e48e77f57b9b352d57.json",
			"kind" : "codemodel",
			"version" : 
			{
				"major" : 2,
				"minor" : 3
			}
		},
		{
			"jsonFile" : "cache-v2-a98b6125d45ae027b95f.json",
			"kind" : "cache",
			"version" : 
			{
				"major" : 2,
				"minor" : 0
			}
		},
		{
			"jsonFile" : "cmakeFiles-v1-fa41da208d0550aec927.json",
			"kind" : "cmakeFiles",
			"version" : 
			{
				"major" : 1,
				"minor" : 0
			}
		},
		{
			"jsonFile" : "toolchains-v1-076db8aff123804178fa.json",
			"kind" : "toolchains",
			"version" : 
			{
				"major" : 1,
				"minor" : 0
			}
		}
	],
	"reply" : 
	{
		"cache-v2" : 
		{
			"jsonFile" : "cache-v2-a98b6125d45ae027b95f.json",
			"kind" : "cache",
			"version" : 
			{
				"major" : 2,
				"minor" : 0
			}
		},
		"cmakeFiles-v1" : 
		{
			"jsonFile" : "cmakeFiles-v1-fa41da208d0550aec927.json",
			"kind" : "cmakeFiles",
			"version" : 
			{
				"major" : 1,
				"minor" : 0
			}
		},
		"codemodel-v2" : 
		{
			"jsonFile" : "codemodel-v2-d9e48e77f57b9b352d57.json",
			"kind" : "codemodel",
			"version" : 
			{
				"major" : 2,
				"minor" : 3
			}
		},
		"toolchains-v1" : 
		{
			"jsonFile" : "toolchains-v1-076db8aff123804178fa.json",
			"kind" : "toolchains",
			"version" : 
			{
				"major" : 1,
				"minor" : 0
			}
		}
	}
}
